[
    {
        "name": "Vidhana Soudha, Bangalore, Karnataka",
        "image": "assets/images/020 Vidhana Soudha, Bangalore, Karnataka.jpg",
        "cards": 2
    },
    {
        "name": "Mysore Palace, Mysore, Karnataka (Day View)",
        "image": "assets/images/021 Mysore Palace, Mysore, Karnataka.jpg",
        "cards": 2
    },
    {
        "name": "Mysore Palace, Mysore, Karnataka (Night View)",
        "image": "assets/images/022 Mysore Palace, Mysore, Karnataka.jpg",
        "cards": 2
    },
    {
        "name": "Writers' Building, Kolkata, West Bengal",
        "image": "assets/images/023 Writers Building, Kolkata, West Bengal.jpg",
        "cards": 1
    },
    {
        "name": "Nagore Dargah, Nagapattinam, Tamil Nadu",
        "image": "assets/images/024 Nagore Dargah, Nagapattinam, Tamil Nadu.jpg",
        "cards": 1
    },
    {
        "name": "Ranganathaswamy Temple, Srirangapatna, Karnataka",
        "image": "assets/images/019 Ranganathaswamy Temple, Srirangapatna, Karnataka.jpg",
        "cards": 1,
        "orientation": "portrait",
        "comment": "Taken by @RiverWoman on PC Forum Swap",
        "link": "https://community.postcrossing.com/t/re-offer-unesco-world-heritage-sites-and-tentative-sites-from-india/1053980"
    },
    {
        "name": "Colva Beach, Goa",
        "image": "assets/images/025 Colva Beach, Goa.jpg",
        "cards": 1
    },
    {
        "name": "Juhu Beach, Mumbai, Maharashtra",
        "image": "assets/images/026 Juhu Beach, Mumbai, Maharashtra.jpg",
        "cards": 1
    },
    {
        "name": "Chinese Fishing Net, Cochin, Kerala",
        "image": "assets/images/027 Chinese Fishing Net, Cochin, Kerala.jpg",
        "cards": 1
    },
    {
        "name": "Backwaters, Kerala",
        "image": "assets/images/028 Backwaters, Kerala.jpg",
        "cards": 1
    },
    {
        "name": "Backwaters, Kerala",
        "image": "assets/images/029 Backwaters, Kerala.jpg",
        "cards": 1
    },
    {
        "name": "Backwaters, Kerala",
        "image": "assets/images/030 Backwaters, Kerala.jpg",
        "cards": 1
    },
    {
        "name": "Auto Rickshaw, Hampi, Karnataka",
        "image": "assets/images/031 Auto rickshaw, Hampi, Karnataka.jpg",
        "cards": 1
    },
    {
        "name": "Auto Rickshaw, Kerala",
        "image": "assets/images/032 Auto rickshaw, Kerala.jpg",
        "cards": 2
    },
    {
        "name": "Atul Shakti Cargo, Kutch, Gujarat",
        "image": "assets/images/033 Atul Shakti Cargo, Kutch, Gujarat.jpg",
        "cards": 1,
        "comment": "Taken by @MikaMinsk on PC Forum Tag",
        "link": "https://community.postcrossing.com/t/i-m-offering-you-can-choose-tag-2-part-2/864696/2320"
    },
    {
        "name": "Elephant on the Road, Kerala",
        "image": "assets/images/034 Elephant on the Road, Kerala.jpg",
        "cards": 2
    },
    {
        "name": "Elephant on the Road, Kerala",
        "image": "assets/images/035 Elephant on the Road, Kerala.jpg",
        "cards": 1
    },
    {
        "name": "Elephant on the Road",
        "image": "assets/images/036 Elephant on the Road.jpg",
        "cards": 1
    },
    {
        "name": "Elephant on the Road",
        "image": "assets/images/037 Elephant on the Road.jpg",
        "cards": 0,
        "comment": "Taken by @Cherry_16_rus on PC Forum Tag",
        "link": "https://community.postcrossing.com/t/i-m-offering-you-can-choose-tag-2-part-2/864696/2298"
    },
    {
        "name": "Lakshmi, the Temple Elephant, Hampi, Karnataka",
        "image": "assets/images/038 Lakshmi, the Temple Elephant, Hampi, Karnataka.jpg",
        "cards": 3
    },
    {
        "name": "Temple Elephant, Srirangam, Tamil Nadu",
        "image": "assets/images/039 Temple Elephant, Srirangam, Tamil Nadu.jpg",
        "cards": 2,
        "orientation": "portrait"
    },
    {
        "name": "Bullock Cart on the Road, South India",
        "image": "assets/images/040 Bullock cart on the Road, South India.jpg",
        "cards": 1
    },
    {
        "name": "Bullock Cart on the Road, Goa",
        "image": "assets/images/041 Bullock cart on the Road, Goa.jpg",
        "cards": 1
    },
    {
        "name": "Decorated Bull",
        "image": "assets/images/042 Decorated Bull.jpg",
        "cards": 2,
        "orientation": "portrait"
    },
    {
        "name": "Cow",
        "image": "assets/images/043 Cow.jpg",
        "cards": 0,
        "orientation": "portrait",
        "comment": "Taken by @ellistrations on PC Forum Tag to sent to @CrimsonKing",
        "link": "https://community.postcrossing.com/t/i-m-offering-you-can-choose-tag-2-part-2/864696/2368"
    },
    {
        "name": "Camel and the Owner, Rajasthan",
        "image": "assets/images/044 Camel and the Owner, Rajasthan.jpg",
        "cards": 1,
        "orientation": "portrait",
        "comment": "Taken by @Stella_marina007 on PC Forum Tag",
        "link": "https://community.postcrossing.com/t/i-m-offering-you-can-choose-tag-1-offer-tag-reverse-tag-part-2/864702/2504"
    },
    {
        "name": "Market Place, Goa",
        "image": "assets/images/045 Market Place, Goa.jpg",
        "cards": 2
    },
    {
        "name": "Onion Seller, Goa",
        "image": "assets/images/046 Onion Seller, Goa.jpg",
        "cards": 2
    },
    {
        "name": "Market Place, South India",
        "image": "assets/images/047 Market Place, South India.jpg",
        "cards": 2
    },
    {
        "name": "Market Place, India",
        "image": "assets/images/048 Market Place, India.jpg",
        "cards": 2
    },
    {
        "name": "Flower Seller, Mysore, Karnataka",
        "image": "assets/images/049 Flower Seller, Mysore, Karnataka.jpg",
        "cards": 1
    },
    {
        "name": "Market Place, South India",
        "image": "assets/images/050 Market Place, South India.jpg",
        "cards": 1
    },
    {
        "name": "Banana Market, Kerala",
        "image": "assets/images/051 Banana Market, Kerala.jpg",
        "cards": 1
    },
    {
        "name": "Tikka Market, India",
        "image": "assets/images/052 Tikka Market, India.jpg",
        "cards": 2
    },
    {
        "name": "Tikka Powders, India",
        "image": "assets/images/053 Tikka Powders, India.jpg",
        "cards": 1
    },
    {
        "name": "Market Place, Pune, Maharashtra",
        "image": "assets/images/054 Market Place, Pune, Maharashtra.jpg",
        "cards": 1
    },
    {
        "name": "Market Scene, Goa",
        "image": "assets/images/055 Market Scene, Goa.jpg",
        "cards": 1,
        "orientation": "portrait",
        "comment": "Taken by @conetoiles on PC Forum Swap",
        "link": "https://community.postcrossing.com/t/re-offer-united-nations-cards-with-un-stamps/1055718"
    },
    {
        "name": "Flower Seller, Goa",
        "image": "assets/images/056 Flower Seller, Goa.jpg",
        "cards": 1,
        "orientation": "portrait"
    },
    {
        "name": "Market Scene, India",
        "image": "assets/images/057 Market Scene, India.jpg",
        "cards": 1,
        "orientation": "portrait"
    },
    {
        "name": "Hampi, Karnataka",
        "image": "assets/images/058 Hampi, Karnataka.jpg",
        "cards": 2,
        "orientation": "portrait"
    },
    {
        "name": "Konark Beach, Odisha",
        "image": "assets/images/059 Konark Beach, Odisha.jpg",
        "cards": 2
    },
    {
        "name": "Paddy Plantation, Tamil Nadu",
        "image": "assets/images/060 Paddy Plantation, Tamil Nadu.jpg",
        "cards": 2
    },
    {
        "name": "Paddy Field, Goa",
        "image": "assets/images/061 Paddy Field, Goa.jpg",
        "cards": 1
    },
    {
        "name": "Snake Charmers",
        "image": "assets/images/062 Snake Charmers.jpg",
        "cards": 2
    },
    {
        "name": "Pots Sellers, Rajasthan",
        "image": "assets/images/063 Pots Sellers, Rajasthan.jpg",
        "cards": 1
    },
    {
        "name": "Pushkar, Rajasthan",
        "image": "assets/images/064 Pushkar, Rajasthan.jpg",
        "cards": 1
    },
    {
        "name": "Rajasthan",
        "image": "assets/images/065 Rajasthan.jpg",
        "cards": 1
    },
    {
        "name": "Bharatanatyam Dancer, South India",
        "image": "assets/images/066 Bharatanatyam Dancer, South India.jpg",
        "cards": 2,
        "orientation": "portrait"
    },
    {
        "name": "Radha and Krisna",
        "image": "assets/images/067 Radha and Krisna.jpg",
        "cards": 1,
        "orientation": "portrait"
    },
    {
        "name": "Map of India",
        "image": "assets/images/068 Map of India.jpg",
        "cards": 1,
        "orientation": "portrait"
    },
    {
        "name": "The Historic Ensemble of Orchha, Madhya Pradesh (Orchha City)",
        "image": "assets/images/012 Orchha City.jpg",
        "tag": "UNESCO Tentative",
        "cards": 1,
        "comment": "Taken by @Xiaoi on PC Forum Swap",
        "link": "https://community.postcrossing.com/t/re-offer-unesco-world-heritage-sites-and-tentative-sites-from-india/1054748"
    },
    {
        "name": "The Historic Ensemble of Orchha, Madhya Pradesh (Chhatri, Orchha)",
        "image": "assets/images/013 Chhatri Orchha.jpg",
        "tag": "UNESCO Tentative",
        "cards": 2
    },
    {
        "name": "Evolution of Temple Architecture – Aihole-Badami-Pattadakal, Karnataka (Cave Temple, Badami)",
        "image": "assets/images/014 Cave Temple, Badami.jpg",
        "tag": "UNESCO Tentative",
        "cards": 1,
        "comment": "Taken by @Beat on PC Forum Swap",
        "link": "https://community.postcrossing.com/t/re-offer-unesco-world-heritage-sites-and-tentative-sites-from-india/1054090"
    },
    {
        "name": "Evolution of Temple Architecture – Aihole-Badami-Pattadakal, Karnataka (Agastya Lake, Badami)",
        "image": "assets/images/015 Agastya Lake, Badami.jpg",
        "tag": "UNESCO Tentative",
        "cards": 1
    },
    {
        "name": "Sri Ranganathaswamy Temple, Srirangam, Tamil Nadu",
        "image": "assets/images/016 Sri Ranganathaswamy Temple, Srirangam, Tamil Nadu.jpg",
        "tag": "UNESCO Tentative",
        "cards": 2,
        "orientation": "portrait"
    },
    {
        "name": "Sri Ranganathaswamy Temple, Srirangam, Tamil Nadu (Temple Pillars)",
        "image": "assets/images/017 Temple Pillars, Srirangam, Tamil Nadu.jpg",
        "tag": "UNESCO Tentative",
        "cards": 1
    },
    {
        "name": "Temples of Kanchipuram, Tamil Nadu (Varadharaja Perumal Temple, Kanchipuram)",
        "image": "assets/images/018 Varadharaja Perumal Temple, Kanchipuram.jpg",
        "tag": "UNESCO Tentative",
        "cards": 2
    },
    {
        "name": "Taj Mahal, Uttar Pradesh",
        "image": "assets/images/001 Taj Mahal, Uttar Pradesh.jpg",
        "tag": "UNESCO WHS",
        "cards": 2
    },
    {
        "name": "Sacred Ensembles of the Hoysalas, Karnataka (Chennakeshava Temple, Somanathapura)",
        "image": "assets/images/002 Chennakeshava Temple, Somanathapura.jpg",
        "tag": "UNESCO WHS",
        "cards": 2
    },
    {
        "name": "Sacred Ensembles of the Hoysalas, Karnataka",
        "image": "assets/images/011 Sacred Ensembles of the Hoysalas.jpg",
        "tag": "UNESCO WHS",
        "cards": 1,
        "orientation": "portrait"
    },
    {
        "name": "Group of Monuments at Hampi, Karnataka (Virupaksha Temple, Hampi)",
        "image": "assets/images/003 Virupaksha Temple, Hampi.jpg",
        "tag": "UNESCO WHS",
        "cards": 1
    },
    {
        "name": "Group of Monuments at Hampi, Karnataka (Pushkarani or Water Tank, Hampi)",
        "image": "assets/images/004 Pushkarani or Water Tank, Hampi.jpg",
        "tag": "UNESCO WHS",
        "cards": 1
    },
    {
        "name": "Group of Monuments at Hampi, Karnataka",
        "image": "assets/images/005 Group of Monuments at Hampi, Karnataka.jpg",
        "tag": "UNESCO WHS",
        "cards": 1
    },
    {
        "name": "Group of Monuments at Mahabalipuram, Tamil Nadu (Shore Temple, Mahabalipuram)",
        "image": "assets/images/006 Group of Monuments at Mahabalipuram, Tamil Nadu (Shore Temple, Mahabalipuram).jpg",
        "tag": "UNESCO WHS",
        "cards": 1
    },
    {
        "name": "Great Living Chola Temples, Tamil Nadu (Brihadisvara Temple, Thanjavur)",
        "image": "assets/images/007 Great Living Chola Temples, Tamil Nadu (Brihadisvara Temple, Thanjavur).jpg",
        "tag": "UNESCO WHS",
        "cards": 1,
        "comment": "Taken by @aletterbox on PC Forum Swap",
        "link": "https://community.postcrossing.com/t/re-offer-unesco-world-heritage-sites-and-tentative-sites-from-india/1054093"
    },
    {
        "name": "Great Living Chola Temples, Tamil Nadu (Brihadisvara Temple, Thanjavur)",
        "image": "assets/images/008 Great Living Chola Temples, Tamil Nadu (Brihadisvara Temple, Thanjavur).jpg",
        "tag": "UNESCO WHS",
        "cards": 1
    },
    {
        "name": "Great Living Chola Temples, Tamil Nadu (Gangaikonda Cholapuram)",
        "image": "assets/images/009 Great Living Chola Temples, Tamil Nadu (Gangaikonda Cholapuram).jpg",
        "tag": "UNESCO WHS",
        "cards": 2
    },
    {
        "name": "Jaipur City, Rajasthan",
        "image": "assets/images/010 Jaipur City, Rajasthan.jpg",
        "tag": "UNESCO WHS",
        "cards": 1,
        "orientation": "portrait",
        "comment": "Taken by @Bagheera on PC Forum Swap",
        "link": "https://community.postcrossing.com/t/re-offer-unesco-world-heritage-sites-and-tentative-sites-from-india/1053703"
    }
]